MANIFEST.in
setup.cfg
setup.py
collective/__init__.py
collective.theme.iwaters.egg-info/PKG-INFO
collective.theme.iwaters.egg-info/SOURCES.txt
collective.theme.iwaters.egg-info/dependency_links.txt
collective.theme.iwaters.egg-info/entry_points.txt
collective.theme.iwaters.egg-info/namespace_packages.txt
collective.theme.iwaters.egg-info/not-zip-safe
collective.theme.iwaters.egg-info/requires.txt
collective.theme.iwaters.egg-info/top_level.txt
collective/theme/__init__.py
collective/theme/iwaters/README.txt
collective/theme/iwaters/__init__.py
collective/theme/iwaters/config.py
collective/theme/iwaters/configure.zcml
collective/theme/iwaters/mkstatic.sh
collective/theme/iwaters/skins.zcml
collective/theme/iwaters/tests.py
collective/theme/iwaters/version.txt
collective/theme/iwaters/browser/__init__.py
collective/theme/iwaters/browser/configure.zcml
collective/theme/iwaters/browser/footer.pt
collective/theme/iwaters/browser/interfaces.py
collective/theme/iwaters/browser/viewlets.py
collective/theme/iwaters/docs/__init__.py
collective/theme/iwaters/docs/browser.txt
collective/theme/iwaters/profiles/default/actions.xml
collective/theme/iwaters/profiles/default/browserlayer.xml
collective/theme/iwaters/profiles/default/collective.theme.iwaters.txt
collective/theme/iwaters/profiles/default/cssregistry.xml
collective/theme/iwaters/profiles/default/jsregistry.xml
collective/theme/iwaters/profiles/default/metadata.xml
collective/theme/iwaters/profiles/default/skins.xml
collective/theme/iwaters/profiles/default/theme.xml
collective/theme/iwaters/profiles/uninstall/actions.xml
collective/theme/iwaters/profiles/uninstall/browserlayer.xml
collective/theme/iwaters/profiles/uninstall/collective.theme.iwaters.txt
collective/theme/iwaters/profiles/uninstall/cssregistry.xml
collective/theme/iwaters/profiles/uninstall/jsregistry.xml
collective/theme/iwaters/profiles/uninstall/skins.xml
collective/theme/iwaters/profiles/uninstall/theme.xml
collective/theme/iwaters/skins/images/CONTENT.txt
collective/theme/iwaters/skins/javascripts/CONTENT.txt
collective/theme/iwaters/skins/styles/CONTENT.txt
collective/theme/iwaters/skins/templates/CONTENT.txt
collective/theme/iwaters/skins/templates/hasobject.py
collective/theme/iwaters/static/index.html
collective/theme/iwaters/static/manifest.cfg
collective/theme/iwaters/static/rules.xml
