Metadata-Version: 1.0
Name: collective.theme.iwaters
Version: 0.3
Summary: Theme derived from IW:LEARN theme
Home-page: http://plone.org/products/collective.theme.iwaters
Author: Christian Ledermann
Author-email: christian.ledermann@gmail.com
License: GPL
Keywords: web zope plone theme skin
Platform: UNKNOWN
Classifier: Framework :: Plone
Classifier: Framework :: Plone :: 4.1
Classifier: Framework :: Plone :: 4.2
Classifier: Framework :: Zope2
Classifier: Framework :: Zope3
Classifier: Programming Language :: Python
Classifier: Development Status :: 5 - Production/Stable
